pyss/__init__.py
pySafeSave-0.2.dist-info/METADATA
pySafeSave-0.2.dist-info/WHEEL
pySafeSave-0.2.dist-info/top_level.txt
pySafeSave-0.2.dist-info/RECORD
