Metadata-Version: 2.1
Name: pySafeSave
Version: 0.2
Summary: Python module to store data and encrypt it with two security layers.
Author: LowRezCat (Ivan Resetnikov)
Author-email: ivan.resetnikov.alpha@gmail.com
Keywords: python,save,safe,write,encrypt,encode,security
Classifier: Development Status :: 5 - Production/Stable
Classifier: Intended Audience :: Developers
Classifier: Programming Language :: Python :: 3
Classifier: Operating System :: Unix
Classifier: Operating System :: MacOS :: MacOS X
Classifier: Operating System :: Microsoft :: Windows
